<plugin class="motl" headersize="92">
  <revisions>
    <revision author="DarkShallFall" version="0.1">Mapped plugin structure a new.</revision>
    <revision author="Snipe" version="0.6">Named Structs And Indexes.</revision>
    <revision author="Snipe" version="0.75">Added Chunk Lists, Icons And Renamed Structs.</revision>
  </revisions>
  <struct name="Game Variant Objects" offset="0" visible="True" size="20">
    <stringID name="Identifier" offset="0" visible="True" />
    <tagRef name="Related Object" offset="4" visible="True" />
  </struct>
  <struct name="Game Variant Weapons" offset="12" visible="True" size="16">
    <int32 name="Object Index" offset="0" visible="True" />
    <undefined name="Unknown" offset="4" visible="False" />
    <float32 name="Unknown" offset="8" visible="False" />
    <enum32 name="Weapon Icon" offset="12" visible="True">
      <option name="Dmr" value="0" />
      <option name="Assault Rifle" value="1" />
      <option name="Plasma Pistol" value="2" />
      <option name="Spike Rifle" value="3" />
      <option name="Smg" value="4" />
      <option name="Energy Sword" value="5" />
      <option name="Magnum" value="6" />
      <option name="Needler" value="7" />
      <option name="Plasma Rifle" value="8" />
      <option name="Rocket Launcher" value="9" />
      <option name="Shotgun" value="10" />
      <option name="Sniper Rifle" value="11" />
      <option name="Grenade Launcher" value="12" />
      <option name="Focus Rifle" value="13" />
      <option name="Spartan Laser" value="14" />
      <option name="Gravity Hammer" value="15" />
      <option name="Mauler" value="16" />
      <option name="Flamethrower" value="17" />
      <option name="Golf Club 2" value="18" />
      <option name="Plasma Repeater" value="19" />
      <option name="Needle Rifle" value="20" />
      <option name="Focus Rifle 2" value="21" />
      <option name="Plasma Launcher" value="22" />
      <option name="Concussion Rifle" value="23" />
      <option name="Grenade Launcher 2" value="24" />
      <option name="Golf Club" value="25" />
      <option name="Fuel Rod Gun" value="26" />
      <option name="Question Mark / Random" value="27" />
    </enum32>
  </struct>
  <struct name="Game Variant Vehicles" offset="24" visible="True" size="16">
    <int32 name="Object Index" offset="0" visible="True" />
    <undefined name="Unknown" offset="4" visible="False" />
    <undefined name="Unknown" offset="8" visible="False" />
    <int32 name="Vehicle Icon" offset="8" visible="True" />
  </struct>
  <struct name="Game Variant Grenades" offset="36" visible="True" size="16">
    <int32 name="Object Index" offset="0" visible="True" />
    <undefined name="Unknown" offset="4" visible="False" />
    <undefined name="Unknown" offset="8" visible="False" />
    <enum32 name="Grenade Icon" offset="12" visible="True">
      <option name="Plasma Grenade" value="0" />
      <option name="Frag Grenade" value="1" />
    </enum32>
  </struct>
  <struct name="Game Variant Equipment" offset="48" visible="True" size="16">
    <int32 name="Object Index" offset="0" visible="True" />
    <undefined name="Unknown" offset="4" visible="False" />
    <undefined name="Unknown" offset="8" visible="False" />
    <int32 name="Equipment Icon" offset="12" visible="True" />
  </struct>
  <struct name="Weapons On Map" offset="60" visible="True" size="16">
    <stringID name="Variant" offset="0" visible="True" />
    <struct name="Not Permitted Weapons" offset="4" visible="True" size="8">
      <int32 name="Weapon Index" offset="0" visible="True" />
      <int32 name="Replacement Weapon Index" offset="4" visible="True" />
    </struct>
  </struct>
  <struct name="Vehicles On Map" offset="72" visible="True" size="16">
    <stringID name="Variant" offset="0" visible="True" />
    <struct name="Not Permitted Vehicles" offset="4" visible="True" size="8">
      <int32 name="Vehicle Index" offset="0" visible="True" />
      <int32 name="Replacement Vehicle Index" offset="4" visible="True" />
    </struct>
  </struct>
  <int32 name="Unknown" offset="84" visible="True" />
  <int32 name="Unknown" offset="88" visible="True" />
</plugin>