<plugin>
  <revisions />
  <struct name="Effects" offset="0x0" visible="True" size="0x18">
    <struct name="Old Materials (Do Not Use)" offset="0x0" visible="True" size="0x18">
      <tagRef name="Effect" offset="0x0" visible="True" />
      <tagRef name="Sound" offset="0x8" visible="True" />
      <stringID name="Material Name" offset="0x10" visible="True" />
      <enum32 name="Sweetener Mode" offset="0x14" visible="True">
        <option name="Default" value="0x0" />
        <option name="Enabled" value="0x1" />
        <option name="Disabled" value="0x2" />
      </enum32>
    </struct>
    <struct name="Sounds" offset="0x8" visible="True" size="0x18">
      <tagRef name="Sound 1" offset="0x0" visible="True" />
      <tagRef name="Sound 2" offset="0x8" visible="True" />
      <stringID name="Material Name" offset="0x10" visible="True" />
      <enum32 name="Sweetener Mode" offset="0x14" visible="True">
        <option name="Default" value="0x0" />
        <option name="Enabled" value="0x1" />
        <option name="Disabled" value="0x2" />
      </enum32>
    </struct>
    <struct name="Effects" offset="0x10" visible="True" size="0x18">
      <tagRef name="Effect 1" offset="0x0" visible="True" />
      <tagRef name="Effect 2" offset="0x8" visible="True" />
      <stringID name="Material Name" offset="0x10" visible="True" />
      <enum32 name="Sweetener Mode" offset="0x14" visible="True">
        <option name="Default" value="0x0" />
        <option name="Enabled" value="0x1" />
        <option name="Disabled" value="0x2" />
      </enum32>
    </struct>
  </struct>
</plugin>